README.rst
setup.py
sphinxcadquery/__init__.py
sphinxcadquery/sphinxcadquery.py
sphinxcadquery.egg-info/PKG-INFO
sphinxcadquery.egg-info/SOURCES.txt
sphinxcadquery.egg-info/dependency_links.txt
sphinxcadquery.egg-info/requires.txt
sphinxcadquery.egg-info/top_level.txt
sphinxcadquery/sphinxcadquerystatic/AMFLoader.js
sphinxcadquery/sphinxcadquerystatic/LegacyJSONLoader.js
sphinxcadquery/sphinxcadquerystatic/OrbitControls.js
sphinxcadquery/sphinxcadquerystatic/STLLoader.js
sphinxcadquery/sphinxcadquerystatic/WebGL.js
sphinxcadquery/sphinxcadquerystatic/jszip.min.js
sphinxcadquery/sphinxcadquerystatic/main.css
sphinxcadquery/sphinxcadquerystatic/main.js
sphinxcadquery/sphinxcadquerystatic/three.js