Metadata-Version: 1.1
Name: sphinxcadquery
Version: 1.3.2
Summary: An extension to visualize CadQuery 3D parts in your Sphinx documentation
Home-page: https://github.com/Peque/sphinxcadquery
Author: Miguel Sánchez de León Peque
Author-email: peque@neosit.es
License: BSD License
Platform: UNKNOWN
Classifier: Development Status :: 4 - Beta
Classifier: Intended Audience :: Developers
Classifier: Topic :: Documentation
Classifier: Topic :: Software Development
Classifier: Topic :: Utilities
Classifier: License :: OSI Approved :: BSD License
Classifier: Operating System :: OS Independent
Classifier: Programming Language :: Python :: 3
Classifier: Framework :: Sphinx :: Extension
